setup.py
distributions_monish/Binomialdistribution.py
distributions_monish/Gaussiandistribution.py
distributions_monish/Generaldistribution.py
distributions_monish/__init__.py
distributions_monish.egg-info/PKG-INFO
distributions_monish.egg-info/SOURCES.txt
distributions_monish.egg-info/dependency_links.txt
distributions_monish.egg-info/not-zip-safe
distributions_monish.egg-info/top_level.txt